[
    {
        "id": 46,
        "imagen": "../assets/img/vinos/Salentein_Malbec.jpg",
        "descripcion": "Vino Salentein Malbec 750ml",
        "unidadMedida": "botella",
        "precio": 1.39
    },
    {
        "id": 47,
        "imagen": "../assets/img/vinos/Salentein_Blanc_de_blancs.jpg",
        "descripcion": "Vino Salentein Blanc de blancs 750ml",
        "unidadMedida": "botella",
        "precio": 990
    },
    {
        "id": 48,
        "imagen": "../assets/img/vinos/Zuccardi_Q_Malbec.jpg",
        "descripcion": "Vino Zuccardi Q Malbec 750ml",
        "unidadMedida": "botella",
        "precio": 2.13
    },
    {
        "id": 49,
        "imagen": "../assets/img/vinos/Salentein_Numina_Cabernet_Franc.jpg",
        "descripcion": "Vino Salentein Numina Cabernet Franc 750ml",
        "unidadMedida": "botella",
        "precio": 2.27
    },
    {
        "id": 50,
        "imagen": "../assets/img/vinos/DV_Catena_Cabernet_Malbec.jpg",
        "descripcion": "Vino DV Catena Cabernet - Malbec 750ml",
        "unidadMedida": "botella",
        "precio": 2.19
    },
    {
        "id": 51,
        "imagen": "../assets/img/vinos/Animal_Malbec.jpg",
        "descripcion": "Vino Animal Malbec 750ml",
        "unidadMedida": "botella",
        "precio": 1.49
    },
    {
        "id": 52,
        "imagen": "../assets/img/vinos/Dv_Catena_Malbec_Malbec.jpg",
        "descripcion": "Vino Dv Catena Malbec - Malbec 750ml",
        "unidadMedida": "botella",
        "precio": 3.99
    },
    {
        "id": 53,
        "imagen": "../assets/img/vinos/Salentein_Numina_Malbec.jpg",
        "descripcion": "Vino Salentein Numina Malbec 750ml",
        "unidadMedida": "botella",
        "precio": 2.27
    },
    {
        "id": 54,
        "imagen": "../assets/img/vinos/Zuccardi_Q_Tempranillo.jpg",
        "descripcion": "Vino Zuccardi Q Tempranillo 750ml",
        "unidadMedida": "botella",
        "precio": 2.13
    }
]